jupyterlab_trame_manager/__init__.py
jupyterlab_trame_manager/_version.py
jupyterlab_trame_manager/cmd.py
jupyterlab_trame_manager/model.py
jupyterlab_trame_manager/proxy.py
jupyterlab_trame_manager/types.py
jupyterlab_trame_manager/configurations/__init__.py
jupyterlab_trame_manager/configurations/desktop.py
jupyterlab_trame_manager/configurations/jsc/__init__.py
jupyterlab_trame_manager/configurations/jsc/paraview_juwelsbooster.in
jupyterlab_trame_manager/handlers/__init__.py
jupyterlab_trame_manager/handlers/paraview.py
jupyterlab_trame_manager/handlers/trame.py
jupyterlab_trame_manager/handlers/user.py
jupyterlab_trame_manager-0.6.1.data/data/etc/jupyter/jupyter_server_config.d/jupyterlab-trame-manager.json
jupyterlab_trame_manager-0.6.1.data/data/share/jupyter/labextensions/jupyterlab-trame-manager/package.json
jupyterlab_trame_manager-0.6.1.data/data/share/jupyter/labextensions/jupyterlab-trame-manager/schemas/jupyterlab-trame-manager/package.json.orig
jupyterlab_trame_manager-0.6.1.data/data/share/jupyter/labextensions/jupyterlab-trame-manager/schemas/jupyterlab-trame-manager/plugin.json
jupyterlab_trame_manager-0.6.1.data/data/share/jupyter/labextensions/jupyterlab-trame-manager/static/105.bd639c7c3059f2c4ee25.js
jupyterlab_trame_manager-0.6.1.data/data/share/jupyter/labextensions/jupyterlab-trame-manager/static/233.f6a6ebfa238596baf0d6.js
jupyterlab_trame_manager-0.6.1.data/data/share/jupyter/labextensions/jupyterlab-trame-manager/static/614.daa35d25376a89428000.js
jupyterlab_trame_manager-0.6.1.data/data/share/jupyter/labextensions/jupyterlab-trame-manager/static/728.88dbdeedfd4afccba21c.js
jupyterlab_trame_manager-0.6.1.data/data/share/jupyter/labextensions/jupyterlab-trame-manager/static/remoteEntry.ad96a60e703c0dd761b9.js
jupyterlab_trame_manager-0.6.1.data/data/share/jupyter/labextensions/jupyterlab-trame-manager/static/style.js
jupyterlab_trame_manager-0.6.1.dist-info/METADATA
jupyterlab_trame_manager-0.6.1.dist-info/WHEEL
jupyterlab_trame_manager-0.6.1.dist-info/licenses/LICENSE
jupyterlab_trame_manager-0.6.1.dist-info/RECORD
