Metadata-Version: 2.3
Name: jupyterlab-trame-manager
Version: 0.6.1
Dynamic: Keywords
Summary: A JupyterLab extension.
Project-URL: Homepage, https://github.com/jwindgassen/jupyterlab-trame-manager
Project-URL: Bug Tracker, https://github.com/jwindgassen/jupyterlab-trame-manager/issues
Project-URL: Repository, https://github.com/jwindgassen/jupyterlab-trame-manager.git
Author-email: Jonathan Windgassen <j.windgassen@fz-juelich.de>
License: BSD 3-Clause License
License-File: LICENSE
Classifier: Framework :: Jupyter
Classifier: Framework :: Jupyter :: JupyterLab
Classifier: Framework :: Jupyter :: JupyterLab :: 4
Classifier: Framework :: Jupyter :: JupyterLab :: Extensions
Classifier: Framework :: Jupyter :: JupyterLab :: Extensions :: Prebuilt
Classifier: License :: OSI Approved :: BSD License
Classifier: Programming Language :: Python
Classifier: Programming Language :: Python :: 3
Classifier: Programming Language :: Python :: 3.10
Classifier: Programming Language :: Python :: 3.11
Classifier: Programming Language :: Python :: 3.12
Requires-Python: >=3.10
Requires-Dist: jupyter-server-proxy>=4.1
Requires-Dist: jupyter-server<3,>=2.0.1
